qt_sass_theme/__init__.py
qt_sass_theme/icon.py
qt_sass_theme/qtSassTheme.py
qt_sass_theme/ico/__init__.py
qt_sass_theme/ico/_icons.scss
qt_sass_theme/ico/check.svg
qt_sass_theme/ico/circle-solid.svg
qt_sass_theme/ico/close.svg
qt_sass_theme/ico/down.svg
qt_sass_theme/ico/drawer.svg
qt_sass_theme/ico/left.svg
qt_sass_theme/ico/right.svg
qt_sass_theme/ico/search.svg
qt_sass_theme/ico/undock.svg
qt_sass_theme/ico/up.svg
qt_sass_theme/sass/__init__.py
qt_sass_theme/sass/custom_widget.scss
qt_sass_theme/sass/icon_button.scss
qt_sass_theme/sass/icon_text_button.scss
qt_sass_theme/sass/menu_bar.scss
qt_sass_theme/sass/theme.scss
qt_sass_theme/var/__init__.py
qt_sass_theme/var/_variables.scss
qt_sass_theme/var/dark/__init__.py
qt_sass_theme/var/dark/dark_blue/__init__.py
qt_sass_theme/var/dark/dark_blue/_variables.scss
qt_sass_theme/var/dark/dark_gray/__init__.py
qt_sass_theme/var/dark/dark_gray/_variables.scss
qt_sass_theme/var/light/__init__.py
qt_sass_theme/var/light/light_blue/__init__.py
qt_sass_theme/var/light/light_blue/_variables.scss
qt_sass_theme/var/light/light_gray/__init__.py
qt_sass_theme/var/light/light_gray/_variables.scss
qtsasstheme-0.0.71.dist-info/LICENSE
qtsasstheme-0.0.71.dist-info/METADATA
qtsasstheme-0.0.71.dist-info/WHEEL
qtsasstheme-0.0.71.dist-info/top_level.txt
qtsasstheme-0.0.71.dist-info/RECORD
