Metadata-Version: 2.1
Name: qtsasstheme
Version: 0.0.71
Summary: Set the Qt theme (e.g. darkgray/lightgray/darkblue/lightblue) easily
Home-page: https://github.com/yjg30737/qtsasstheme.git
Author: Jung Gyu Yoon
Author-email: yjg30737@gmail.com
License: MIT
License-File: LICENSE
Requires-Dist: qtpy
Requires-Dist: qtsass
